logstop/__init__.py
logstop-0.2.0.dist-info/LICENSE.txt
logstop-0.2.0.dist-info/METADATA
logstop-0.2.0.dist-info/WHEEL
logstop-0.2.0.dist-info/top_level.txt
logstop-0.2.0.dist-info/RECORD
