Metadata-Version: 2.1
Name: logstop
Version: 0.2.0
Summary: Keep personal data out of your logs
Author-email: Andrew Kane <andrew@ankane.org>
License: MIT
Project-URL: Homepage, https://github.com/ankane/logstop.py
Requires-Python: >=3.9
License-File: LICENSE.txt
